<?xml version="1.0" encoding="UTF-8" standalone="yes"?>
<templatesConfiguration xmlns="http://capgemini.com/devonfw/cobigen/TemplatesConfiguration"
  xmlns:xsi="http://www.w3.org/2001/XMLSchema-instance" version="2.1">

  <templates>
    <templateExtension ref="${variables.component}addDialog.component.html" mergeStrategy="html-ng*"/>
    <templateExtension ref="${variables.component}addDialog.component.spec.ts"/>
    <templateExtension ref="${variables.component}addDialog.component.ts" mergeStrategy="tsmerge"/>
    <templateExtension ref="${variables.component}addDialog.css"/>
    <templateExtension ref="${variables.component}dataGrid.component.html" mergeStrategy="html-ng*"/>
    <templateExtension ref="${variables.component}dataGrid.component.ts" mergeStrategy="tsmerge"/>
    <templateExtension ref="${variables.component}dataGrid.service.ts" mergeStrategy="tsmerge"/>
    <templateExtension ref="${variables.component}dataGrid.component.spec.ts"/>
    <templateExtension ref="${variables.component}dataGrid.css"/>
    <templateExtension ref="header.component.css"/>
    <templateExtension ref="header.component.spec.ts"/>
    <templateExtension ref="header.component.html"/>
    <templateExtension ref="header.component.ts"/>
    <templateExtension ref="header.service.spec.ts"/>
    <templateExtension ref="header.service.ts"/>
    <templateExtension ref="home.component.html" mergeStrategy="html-ng*"/>
    <templateExtension ref="home.component.css"/>
    <templateExtension ref="home.component.spec.ts"/>
    <templateExtension ref="home.component.ts"/>
    <templateExtension ref="initial-page.component.css"/>
    <templateExtension ref="initial-page.component.html"/>
    <templateExtension ref="initial-page.component.spec.ts"/>
    <templateExtension ref="initial-page.component.ts"/>
    <templateExtension ref="app.module.ts" mergeStrategy="tsmerge"/>
    <templateExtension ref="app.routing.ts" mergeStrategy="tsmerge"/>
    <templateExtension ref="BusinessOperations.ts" mergeStrategy="tsmerge"/>
    <templateExtension ref="es.json" mergeStrategy="jsonmerge"/>
    <templateExtension ref="en.json" mergeStrategy="jsonmerge"/>
    <templateExtension ref="serverPath.ts"/>
  </templates>

  <templateScans>
    <templateScan templatePath="templates" destinationPath="devon4ng2"/>
  </templateScans>

  <increments>
    <increment name="app_angular_structure" description="Angular2 Structure components">
        <templateRef ref="header.component.html"/>
        <templateRef ref="header.component.ts"/>
        <templateRef ref="header.component.css"/>
        <templateRef ref="header.component.spec.ts"/>
        <templateRef ref="header.service.spec.ts"/>
        <templateRef ref="header.service.ts"/>
        <templateRef ref="home.component.html"/>
        <templateRef ref="home.component.ts"/>
        <templateRef ref="home.component.spec.ts"/>
        <templateRef ref="home.component.css"/>
        <templateRef ref="initial-page.component.html"/>
        <templateRef ref="initial-page.component.ts"/>
        <templateRef ref="initial-page.component.spec.ts"/>
        <templateRef ref="initial-page.component.css"/>
        <templateRef ref="serverPath.ts"/>
      </increment>
      <increment name="app_angular_i18n" description="Angular2 i18n">
        <templateRef ref="es.json"/>
        <templateRef ref="en.json"/>
      </increment>
      <increment name="app_angular_oasp4j_component" description="Angular2 OASP4J Component">
        <templateRef ref="${variables.component}addDialog.component.html"/>
        <templateRef ref="${variables.component}addDialog.component.ts"/>
        <templateRef ref="${variables.component}addDialog.component.spec.ts"/>
        <templateRef ref="${variables.component}addDialog.css"/>
        <templateRef ref="${variables.component}dataGrid.component.html"/>
        <templateRef ref="${variables.component}dataGrid.component.ts"/>
        <templateRef ref="${variables.component}dataGrid.service.ts"/>
        <templateRef ref="${variables.component}dataGrid.component.spec.ts"/>
        <templateRef ref="${variables.component}dataGrid.css"/>
        <templateRef ref="BusinessOperations.ts"/>
        <templateRef ref="app.routing.ts"/>
        <templateRef ref="app.module.ts"/>
      </increment>
  </increments>
</templatesConfiguration>
